README.md
setup.py
bin/csrmesh-cli
bin/csrmesh-util
csrmesh/__init__.py
csrmesh/crypto.py
csrmesh/gatt.py
csrmesh/lightbulb.py
csrmesh/movecontroller.py
csrmesh.egg-info/PKG-INFO
csrmesh.egg-info/SOURCES.txt
csrmesh.egg-info/dependency_links.txt
csrmesh.egg-info/not-zip-safe
csrmesh.egg-info/requires.txt
csrmesh.egg-info/top_level.txt