Metadata-Version: 1.1
Name: csrmesh
Version: 0.10.0
Summary: Reverse engineered implementation of the CSRMesh bridge protocol
Home-page: https://github.com/nkaminski/csrmesh
Author: Nash Kaminski, Tomas Salfischberger
Author-email: nashkaminski@kaminski.io, tomas@salfischberger.nl
License: LGPLv3
Keywords: bluetooth csrmesh qualcomm csr BTLE
Platform: UNKNOWN
Classifier: Development Status :: 3 - Alpha
Classifier: Operating System :: POSIX :: Linux
Classifier: License :: OSI Approved :: GNU Lesser General Public License v3 (LGPLv3)
Classifier: Programming Language :: Python :: 3
Classifier: Topic :: Scientific/Engineering :: Interface Engine/Protocol Translator
Classifier: Topic :: Home Automation
